audience/__init__.py
audience/app.py
audience/connections.py
audience/decorators.py
audience/exceptions.py
audience/utils.py
audience_framework-1.0.0.dist-info/licenses/LICENSE
audience_framework-1.0.0.dist-info/METADATA
audience_framework-1.0.0.dist-info/WHEEL
audience_framework-1.0.0.dist-info/top_level.txt
audience_framework-1.0.0.dist-info/RECORD
