Metadata-Version: 2.4
Name: audience-framework
Version: 1.0.0
Summary: A framework for writing asynchronous AMQP-based microservices in Python
Home-page: https://github.com/Neltsoz/audience
Author: Ilya Mushkin
Author-email: mushkin704@gmail.com
License: MIT
Classifier: Programming Language :: Python :: 3
Classifier: Programming Language :: Python :: 3.8
Classifier: Programming Language :: Python :: 3.9
Classifier: Programming Language :: Python :: 3.10
Classifier: Programming Language :: Python :: 3.11
Classifier: Programming Language :: Python :: 3.12
Classifier: Programming Language :: Python :: 3.13
Classifier: Operating System :: OS Independent
Classifier: Topic :: Software Development :: Libraries
Classifier: Topic :: System :: Distributed Computing
Requires-Python: >=3.8
License-File: LICENSE
Requires-Dist: aio-pika==9.5.8
Requires-Dist: aiormq==6.9.2
Requires-Dist: annotated-types==0.7.0
Requires-Dist: idna==3.11
Requires-Dist: multidict==6.7.0
Requires-Dist: pamqp==3.3.0
Requires-Dist: propcache==0.4.1
Requires-Dist: pydantic==2.12.5
Requires-Dist: pydantic-core==2.41.5
Requires-Dist: typing-extensions==4.15.0
Requires-Dist: typing-inspection==0.4.2
Requires-Dist: yarl==1.22.0
Dynamic: license-file
